gspeerconnection/VideoRecorder.py
gspeerconnection/gshlsplayer.py
gspeerconnection/gsmediarecorder.py
gspeerconnection/gsmessenger.py
gspeerconnection/gspeerconnectionbroadcaster.py
gspeerconnection/gspeerconnectionbroadcasterbanana.py
gspeerconnection/gspeerconnectionbroadcasterpi-sync.py
gspeerconnection/gspeerconnectionbroadcasterpi.py
gspeerconnection/gspeerconnectionbroadcasterpisync.py
gspeerconnection/gspeerconnectionbroadcasterpiv3.py
gspeerconnection/gspeerconnectionbroadcasteruniversal.py
gspeerconnection/gspeerconnectionwatcher.py
gspeerconnection/pitrack.py
gs_peer_connection-0.0.31.61.dist-info/METADATA
gs_peer_connection-0.0.31.61.dist-info/WHEEL
gs_peer_connection-0.0.31.61.dist-info/entry_points.txt
gs_peer_connection-0.0.31.61.dist-info/top_level.txt
gs_peer_connection-0.0.31.61.dist-info/RECORD
