Metadata-Version: 2.1
Name: gs-peer-connection
Version: 0.0.31.61
Summary: python peer connection adapter
Home-page: https://glass-sphere-ai.de
Author: Glass Sphere Software
Author-email: 
License: MIT
Platform: UNKNOWN
Classifier: License :: OSI Approved :: MIT License
Classifier: Programming Language :: Python :: 3
Classifier: Programming Language :: Python :: 3.7
Requires-Dist: aiortc
Requires-Dist: aiohttp
Requires-Dist: python-socketio
Requires-Dist: ujson
Requires-Dist: crc32c
Requires-Dist: StrEnum
Requires-Dist: py-ubjson
Requires-Dist: msgpack
Requires-Dist: numpy
Requires-Dist: requests
Requires-Dist: opencv-python
Requires-Dist: PyTurboJPEG
